sheetscrape/__init__.py
sheetscrape/datastructures.py
sheetscrape/parsers/TrainingData.py
sheetscrape/parsers/__init__.py
sheetscrape/scraper.py
sheetscrape/tests/tests.py
sheetscrape-0.1.2.dist-info/LICENSE
sheetscrape-0.1.2.dist-info/WHEEL
sheetscrape-0.1.2.dist-info/METADATA
sheetscrape-0.1.2.dist-info/RECORD
