Metadata-Version: 2.1
Name: sheetscrape
Version: 0.1.2
Summary: Tools for parsing google sheets
License: MIT
Author: Davis Bennett
Author-email: davis.v.bennett@gmail.com
Requires-Python: >=3.7.1,<4
Classifier: License :: OSI Approved :: MIT License
Classifier: Programming Language :: Python :: 3
Classifier: Programming Language :: Python :: 3.8
Classifier: Programming Language :: Python :: 3.9
Requires-Dist: gspread (>=3.6.0,<4.0.0)
Requires-Dist: oauth2client (>=4.1.3,<5.0.0)
Requires-Dist: pandas (>=1.3.4,<2.0.0)
